pytest_tiny_api_client.py
pytest_tiny_api_client-1.0.1.dist-info/LICENSE
pytest_tiny_api_client-1.0.1.dist-info/METADATA
pytest_tiny_api_client-1.0.1.dist-info/WHEEL
pytest_tiny_api_client-1.0.1.dist-info/entry_points.txt
pytest_tiny_api_client-1.0.1.dist-info/top_level.txt
pytest_tiny_api_client-1.0.1.dist-info/RECORD
