Metadata-Version: 2.1
Name: pytest-tiny-api-client
Version: 1.0.1
Summary: The companion pytest plugin for tiny-api-client
Author-email: Jacob Sánchez <jacobszpz@protonmail.com>
Project-URL: Repository, https://github.com/sanjacob/pytest-tiny-api-client
Project-URL: Bug Tracker, https://github.com/sanjacob/pytest-tiny-api-client/issues
Classifier: Development Status :: 5 - Production/Stable
Classifier: Topic :: Internet :: WWW/HTTP
Classifier: Programming Language :: Python :: 3.10
Classifier: Programming Language :: Python :: 3.11
Classifier: Programming Language :: Python :: 3.12
Classifier: License :: OSI Approved :: GNU Lesser General Public License v2 (LGPLv2)
Classifier: Intended Audience :: Developers
Classifier: Operating System :: OS Independent
Classifier: Topic :: Software Development :: Libraries
Requires-Python: >=3.10
License-File: LICENSE
Requires-Dist: pytest
Requires-Dist: tiny-api-client
